{
  "featured": [
    "star-wars",
    "harry-potter",
    "marvel",
    "pixar",
    "disney-classics",
    "the-lord-of-the-rings"
  ],
  "categories": [
    {
      "id": "classics",
      "name": "Classics",
      "packs": [
        "star-wars",
        "harry-potter",
        "the-lord-of-the-rings",
        "bttf-trilogy",
        "marvel"
      ]
    },
    {
      "id": "animated",
      "name": "Animated",
      "packs": [
        "pixar",
        "shrek",
        "disney-classics"
      ]
    }
  ],
  "packs": [
    {
      "id": "star-wars",
      "name": "Star Wars",
      "movieCount": 6
    },
    {
      "id": "harry-potter",
      "name": "Harry Potter",
      "movieCount": 8
    },
    {
      "id": "the-lord-of-the-rings",
      "name": "The Lord of the Rings",
      "movieCount": 3
    },
    {
      "id": "shrek",
      "name": "Shrek",
      "movieCount": 4
    },
    {
      "id": "bttf-trilogy",
      "name": "Back to the Future",
      "movieCount": 3
    },
    {
      "id": "pixar",
      "name": "Pixar",
      "movieCount": 11
    },
    {
      "id": "disney-classics",
      "name": "Disney Classics",
      "movieCount": 13
    },
    {
      "id": "marvel",
      "name": "Marvel",
      "movieCount": 11
    }
  ]
}
