{
  "version": 1,
  "date": "2026-03-30",
  "packId": "the-lord-of-the-rings",
  "puzzle": {
    "targetLine": {
      "character": "BOROMIR",
      "text": "He loves you, Father.",
      "movie": "The Two Towers"
    },
    "contextBefore": {
      "character": "BOROMIR",
      "text": "You give him no credit and yet he tries to do your will."
    },
    "contextAfter": [
      {
        "character": "DENETHOR",
        "text": "Do not trouble me with Faramir. I know his uses, and they are few. We have more urgent things to speak of. Elrond of Rivendell has called a meeting. He will not say why, but I have guessed its purpose. It is rumored that the weapon of the enemy has been found."
      },
      {
        "character": "BOROMIR",
        "text": "The One Ring. Isildur's Bane."
      },
      {
        "character": "DENETHOR",
        "text": "It has fallen into the hands of the Elves. Everyone will try to claim it: Men, Dwarves, wizards. We cannot let that happen. This thing must come to Gondor."
      }
    ]
  },
  "metadata": {
    "movies": [
      "the-lord-of-the-rings-fotr",
      "the-lord-of-the-rings-ttt",
      "the-lord-of-the-rings-rotk"
    ],
    "movieYears": {
      "the-lord-of-the-rings-fotr": 2001,
      "the-lord-of-the-rings-ttt": 2002,
      "the-lord-of-the-rings-rotk": 2003
    },
    "movieTitles": {
      "the-lord-of-the-rings-fotr": "The Fellowship of the Ring",
      "the-lord-of-the-rings-ttt": "The Two Towers",
      "the-lord-of-the-rings-rotk": "The Return of the King"
    },
    "charactersByMovie": {
      "the-lord-of-the-rings-fotr": [
        "ARAGORN",
        "ARWEN",
        "BILBO",
        "BOROMIR",
        "CELEBORN",
        "ELROND",
        "ELVES",
        "FRODO",
        "GALADRIEL",
        "GANDALF",
        "GIMLI",
        "GOLLUM",
        "HALDIR",
        "LEGOLAS",
        "MERRY",
        "MERRY AND PIPPIN",
        "PIPPIN",
        "SAM",
        "SARUMAN",
        "STRIDER"
      ],
      "the-lord-of-the-rings-ttt": [
        "ARAGORN",
        "ARWEN",
        "BOROMIR",
        "CROWD",
        "DENETHOR",
        "ELROND",
        "EOMER",
        "EOWYN",
        "FARAMIR",
        "FRODO",
        "GALADRIEL",
        "GAMLING",
        "GANDALF",
        "GIMLI",
        "GOLLUM",
        "GRÍMA",
        "LEGOLAS",
        "MADRIL",
        "MAN",
        "MAUHÚR",
        "MERRY",
        "MOTHER",
        "PIPPIN",
        "SAM",
        "SARUMAN",
        "SMÉAGOL",
        "THÉODEN",
        "TREEBEARD",
        "UGLÚK",
        "ÈOMER",
        "ÈOWYN"
      ],
      "the-lord-of-the-rings-rotk": [
        "ARAGORN",
        "ARWEN",
        "BILBO",
        "DENETHOR",
        "ELROND",
        "EOMER",
        "EOWYN",
        "FARAMIR",
        "FRODO",
        "GAMLING",
        "GANDALF",
        "GIMLI",
        "GOLLUM",
        "GORBAG",
        "GOTHMOG",
        "LEGOLAS",
        "MERRY",
        "ORC CAPTAIN",
        "PIPPIN",
        "SAM",
        "SARUMAN",
        "SHAGRAT",
        "SMÉAGOL",
        "SOLDIER",
        "THE KING OF THE DEAD",
        "THEODEN",
        "THÉODEN",
        "WITCH-KING",
        "ÉOMER",
        "ÉOWYN"
      ]
    }
  }
}