{
  "version": 1,
  "date": "2026-07-25",
  "packId": "finding-nemo",
  "puzzle": {
    "targetLine": {
      "character": "MARLIN",
      "text": "I said get back here, now!!",
      "movie": "Finding Nemo"
    },
    "contextBefore": {
      "character": "MARLIN",
      "text": "You’re gonna get stuck out there, and I’m gonna have to get you before another fish does! Get back here!"
    },
    "contextAfter": [
      {
        "character": "MARLIN",
        "text": "Stop!"
      },
      {
        "character": "MARLIN",
        "text": "You take one more move, mister...!"
      },
      {
        "character": "MARLIN",
        "text": "D-Don’t you dare, if you put one fin on that boat! Are you listening to me?! Don’t touch the b..."
      }
    ]
  },
  "metadata": {
    "movies": [
      "Finding Nemo",
      "Finding Dory"
    ],
    "movieYears": {
      "Finding Nemo": 2003,
      "Finding Dory": 2016
    },
    "charactersByMovie": {
      "Finding Nemo": [
        "ANCHOR",
        "BLOAT",
        "BOB",
        "BRUCE",
        "BUBBLES",
        "CHUM",
        "CORAL",
        "DARLA",
        "DEB",
        "DORY",
        "GILL",
        "GURGLE",
        "JACQUES",
        "MARLIN",
        "MR. RAY",
        "NEMO",
        "NIGEL",
        "PEACH",
        "PEARL",
        "SHERMAN",
        "TAD"
      ],
      "Finding Dory": [
        "BAILEY",
        "DESTINY",
        "DORY",
        "FLUKE",
        "HANK",
        "MARLIN",
        "NEMO",
        "RUDDER",
        "SIGOURNEY WEAVER",
        "YOUNG DORY"
      ]
    }
  }
}