{
  "version": 1,
  "date": "2026-09-27",
  "packId": "incredibles",
  "puzzle": {
    "targetLine": {
      "character": "GUARD",
      "text": "Think they’re supers?",
      "movie": "The Incredibles"
    },
    "contextBefore": {
      "character": "HELEN (ELASTIGIRL)",
      "text": "I didn’t bring ‘em, they stowed away. And I don’t think you’re striking the proper tone here!"
    },
    "contextAfter": [
      {
        "character": "VIOLET",
        "text": "Dash, remember what Mom said."
      },
      {
        "character": "DASH",
        "text": "What?"
      },
      {
        "character": "GUARD 2",
        "text": "Hey! Stop talking!"
      }
    ]
  },
  "metadata": {
    "movies": [
      "The Incredibles",
      "Incredibles 2"
    ],
    "movieYears": {
      "The Incredibles": 2004,
      "Incredibles 2": 2018
    },
    "charactersByMovie": {
      "The Incredibles": [
        "BERNIE",
        "BOB",
        "BOB (MR. INCREDIBLE)",
        "DASH",
        "E",
        "FROZONE",
        "GUARD",
        "HELEN",
        "HELEN (ELASTIGIRL)",
        "HUPH",
        "KARI",
        "LUCIUS",
        "MIRAGE",
        "POLICE OFFICER",
        "SYNDROME",
        "TONY",
        "VIOLET"
      ],
      "Incredibles 2": [
        "AMBASSADOR",
        "BOB",
        "DASH",
        "EDNA",
        "ELASTIGIRL",
        "EVELYN",
        "FROZONE",
        "HELEN",
        "LUCIUS",
        "MR. INCREDIBLE",
        "RICK",
        "SCREENSLAVER",
        "TONY",
        "UNDERMINER",
        "VIOLET",
        "VOYD",
        "WINSTON"
      ]
    }
  }
}