{
  "version": 1,
  "date": "2026-05-25",
  "packId": "incredibles",
  "puzzle": {
    "targetLine": {
      "character": "MIRAGE",
      "text": "Trust me. This is the one he’s been looking for.",
      "movie": "The Incredibles"
    },
    "contextBefore": {
      "character": "LUCIUS",
      "text": "That was way too close. We are not doing that again."
    },
    "contextAfter": [
      {
        "character": "HELEN",
        "text": "I thought you'd be back by 11."
      },
      {
        "character": "BOB",
        "text": "I said I'd be back later."
      },
      {
        "character": "HELEN",
        "text": "I assumed you’d be back later. If you came back at all...you’d be \"back later\"."
      }
    ]
  },
  "metadata": {
    "movies": [
      "The Incredibles",
      "Incredibles 2"
    ],
    "movieYears": {
      "The Incredibles": 2004,
      "Incredibles 2": 2018
    },
    "charactersByMovie": {
      "The Incredibles": [
        "BERNIE",
        "BOB",
        "BOB (MR. INCREDIBLE)",
        "DASH",
        "E",
        "FROZONE",
        "GUARD",
        "HELEN",
        "HELEN (ELASTIGIRL)",
        "HUPH",
        "KARI",
        "LUCIUS",
        "MIRAGE",
        "POLICE OFFICER",
        "SYNDROME",
        "TONY",
        "VIOLET"
      ],
      "Incredibles 2": [
        "AMBASSADOR",
        "BOB",
        "DASH",
        "EDNA",
        "ELASTIGIRL",
        "EVELYN",
        "FROZONE",
        "HELEN",
        "LUCIUS",
        "MR. INCREDIBLE",
        "RICK",
        "SCREENSLAVER",
        "TONY",
        "UNDERMINER",
        "VIOLET",
        "VOYD",
        "WINSTON"
      ]
    }
  }
}