{
  "version": 1,
  "date": "2027-01-14",
  "packId": "incredibles",
  "puzzle": {
    "targetLine": {
      "character": "BOB",
      "text": "Ice of you to drop by.",
      "movie": "The Incredibles"
    },
    "contextBefore": {
      "character": "BOB",
      "text": "He-hey!"
    },
    "contextAfter": [
      {
        "character": "LUCIUS",
        "text": "Ha! Never heard that one before."
      },
      {
        "character": "DASH",
        "text": "Oh, Lucius!"
      },
      {
        "character": "LUCIUS",
        "text": "Whoa!"
      }
    ]
  },
  "metadata": {
    "movies": [
      "The Incredibles",
      "Incredibles 2"
    ],
    "movieYears": {
      "The Incredibles": 2004,
      "Incredibles 2": 2018
    },
    "charactersByMovie": {
      "The Incredibles": [
        "BERNIE",
        "BOB",
        "BOB (MR. INCREDIBLE)",
        "DASH",
        "E",
        "FROZONE",
        "GUARD",
        "HELEN",
        "HELEN (ELASTIGIRL)",
        "HUPH",
        "KARI",
        "LUCIUS",
        "MIRAGE",
        "POLICE OFFICER",
        "SYNDROME",
        "TONY",
        "VIOLET"
      ],
      "Incredibles 2": [
        "AMBASSADOR",
        "BOB",
        "DASH",
        "EDNA",
        "ELASTIGIRL",
        "EVELYN",
        "FROZONE",
        "HELEN",
        "LUCIUS",
        "MR. INCREDIBLE",
        "RICK",
        "SCREENSLAVER",
        "TONY",
        "UNDERMINER",
        "VIOLET",
        "VOYD",
        "WINSTON"
      ]
    }
  }
}